<?xml version="1.0" encoding="UTF-8"?>
<objects serializationModel="Studio.02.02.00">
	<object class="AudioFile" id="{bebb1248-4d4f-4bf9-a3ab-977afd503ef8}">
		<property name="assetPath">
			<value>terraria/07. Desert.mp3</value>
		</property>
		<property name="isStreaming">
			<value>true</value>
		</property>
		<property name="frequencyInKHz">
			<value>44.0999985</value>
		</property>
		<property name="channelCount">
			<value>2</value>
		</property>
		<property name="length">
			<value>89.652244897959179</value>
		</property>
		<relationship name="masterAssetFolder">
			<destination>{3ec376c7-9dab-4e28-9892-9388771afac6}</destination>
		</relationship>
	</object>
</objects>
